cdk_extensions/__init__.py
cdk_extensions/py.typed
cdk_extensions/_jsii/__init__.py
cdk_extensions/_jsii/cdk-extensions@0.0.96.jsii.tgz
cdk_extensions/alerting/__init__.py
cdk_extensions/aps/__init__.py
cdk_extensions/asserts/__init__.py
cdk_extensions/athena/__init__.py
cdk_extensions/config/__init__.py
cdk_extensions/config_rules/__init__.py
cdk_extensions/core/__init__.py
cdk_extensions/ec2/__init__.py
cdk_extensions/ec2_patterns/__init__.py
cdk_extensions/eks_patterns/__init__.py
cdk_extensions/glue/__init__.py
cdk_extensions/glue_tables/__init__.py
cdk_extensions/guardduty/__init__.py
cdk_extensions/k8s_aws/__init__.py
cdk_extensions/k8s_fargate/__init__.py
cdk_extensions/kinesis_firehose/__init__.py
cdk_extensions/lambda_/__init__.py
cdk_extensions/networkmanager/__init__.py
cdk_extensions/ram/__init__.py
cdk_extensions/ram_resources/__init__.py
cdk_extensions/rds/__init__.py
cdk_extensions/resourcegroups/__init__.py
cdk_extensions/route53/__init__.py
cdk_extensions/s3_buckets/__init__.py
cdk_extensions/securityhub/__init__.py
cdk_extensions/securityhub_patterns/__init__.py
cdk_extensions/ssm/__init__.py
cdk_extensions/sso/__init__.py
cdk_extensions/stacks/__init__.py
cdk_extensions/stepfunctions/__init__.py
cdk_extensions-0.0.96.data/scripts/init-aws.sh
cdk_extensions-0.0.96.dist-info/LICENSE
cdk_extensions-0.0.96.dist-info/METADATA
cdk_extensions-0.0.96.dist-info/WHEEL
cdk_extensions-0.0.96.dist-info/top_level.txt
cdk_extensions-0.0.96.dist-info/RECORD
